README.md
setup.py
src/xreload.py
src/xreload.egg-info/PKG-INFO
src/xreload.egg-info/SOURCES.txt
src/xreload.egg-info/dependency_links.txt
src/xreload.egg-info/pbr.json
src/xreload.egg-info/top_level.txt